garpix_admin_lock/MANIFEST.in
garpix_admin_lock/README.md
garpix_admin_lock/__init__.py
garpix_admin_lock/admin.py
garpix_admin_lock/apps.py
garpix_admin_lock/handlers.py
garpix_admin_lock/settings.py
garpix_admin_lock/setup.py
garpix_admin_lock/urls.py
garpix_admin_lock/utils.py
garpix_admin_lock/views.py
garpix_admin_lock/__pycache__/__init__.cpython-38.pyc
garpix_admin_lock/__pycache__/admin.cpython-38.pyc
garpix_admin_lock/__pycache__/apps.cpython-38.pyc
garpix_admin_lock/__pycache__/settings.cpython-38.pyc
garpix_admin_lock/__pycache__/urls.cpython-38.pyc
garpix_admin_lock/__pycache__/utils.cpython-38.pyc
garpix_admin_lock/__pycache__/views.cpython-38.pyc
garpix_admin_lock/mixins/__init__.py
garpix_admin_lock/mixins/admin_mixin.py
garpix_admin_lock/mixins/base_mixin.py
garpix_admin_lock/mixins/view_mixin.py
garpix_admin_lock/mixins/__pycache__/__init__.cpython-38.pyc
garpix_admin_lock/mixins/__pycache__/admin_mixin.cpython-38.pyc
garpix_admin_lock/mixins/__pycache__/base_mixin.cpython-38.pyc
garpix_admin_lock/mixins/__pycache__/view_mixin.cpython-38.pyc
garpix_admin_lock/models/__init__.py
garpix_admin_lock/models/base_model.py
garpix_admin_lock/models/database_model.py
garpix_admin_lock/models/redis_model.py
garpix_admin_lock/models/__pycache__/__init__.cpython-38.pyc
garpix_admin_lock/models/__pycache__/base_model.cpython-38.pyc
garpix_admin_lock/models/__pycache__/database_model.cpython-38.pyc
garpix_admin_lock/static/css/page_lock.css
garpix_admin_lock/static/js/page_lock.js
garpix_admin_lock/templates/garpix_admin_lock/page_lock_bar_bootstrap.html
garpix_admin_lock/templates/garpix_admin_lock/page_lock_bar_plain.html
garpix_admin_lock/templates/garpix_admin_lock/admin/page_change_form.html
garpix_admin_lock/templatetags/__init__.py
garpix_admin_lock/templatetags/page_lock_bar.py
garpix_admin_lock/templatetags/__pycache__/__init__.cpython-38.pyc
garpix_admin_lock/templatetags/__pycache__/page_lock_bar.cpython-38.pyc
garpix_admin_lock-1.3.2.dist-info/METADATA
garpix_admin_lock-1.3.2.dist-info/WHEEL
garpix_admin_lock-1.3.2.dist-info/top_level.txt
garpix_admin_lock-1.3.2.dist-info/RECORD
