Metadata-Version: 2.1
Name: garpix-admin-lock
Version: 1.3.2
Home-page: https://github.com/garpixcms/garpix_admin_lock
Author: Garpix LTD
Author-email: info@garpix.com
License: MIT
Classifier: Development Status :: 4 - Beta
Classifier: Environment :: Web Environment
Classifier: Intended Audience :: Developers
Classifier: License :: OSI Approved :: MIT License
Classifier: Operating System :: OS Independent
Classifier: Programming Language :: Python
Classifier: Framework :: Django
Classifier: Programming Language :: Python :: 3.8
Requires-Dist: Django (<5,>=1.11)
